mercury/__init__.py
mercury/ansiblex.py
mercury/base_classes.py
mercury/checkutils.py
mercury/cli_tools.py
mercury/code_templates.py
mercury/configtargets.py
mercury/configtemplates.py
mercury/constants.py
mercury/context.py
mercury/core.py
mercury/csvutils.py
mercury/dataload.py
mercury/datamap.py
mercury/dgen_dates.py
mercury/edcore.py
mercury/elastic.py
mercury/forge.py
mercury/jobs.py
mercury/journaling.py
mercury/mercury_docs.py
mercury/metaobjects.py
mercury/metl_utils.py
mercury/mkinitfile.py
mercury/mklauncher.py
mercury/mkpipeline.py
mercury/mks3notify.py
mercury/mlog.py
mercury/monitoring.py
mercury/mxtypes.py
mercury/objectstore.py
mercury/profiling.py
mercury/services.py
mercury/sqldbx.py
mercury/templateutils.py
mercury/uisequences.py
mercury/utils.py
mercury/xfile_utils.py
mercury_toolkit-0.9.86.data/scripts/beekeeper
mercury_toolkit-0.9.86.data/scripts/bqexport
mercury_toolkit-0.9.86.data/scripts/bqexport-view
mercury_toolkit-0.9.86.data/scripts/bqstream-dl
mercury_toolkit-0.9.86.data/scripts/bqviewtblcreate
mercury_toolkit-0.9.86.data/scripts/bqviewtblscan
mercury_toolkit-0.9.86.data/scripts/cfiltr
mercury_toolkit-0.9.86.data/scripts/chunkr
mercury_toolkit-0.9.86.data/scripts/collapsr
mercury_toolkit-0.9.86.data/scripts/combinatr
mercury_toolkit-0.9.86.data/scripts/couchtalk
mercury_toolkit-0.9.86.data/scripts/countup
mercury_toolkit-0.9.86.data/scripts/csvreorder
mercury_toolkit-0.9.86.data/scripts/csvstack
mercury_toolkit-0.9.86.data/scripts/cyclops
mercury_toolkit-0.9.86.data/scripts/datetimecalc
mercury_toolkit-0.9.86.data/scripts/dfproc
mercury_toolkit-0.9.86.data/scripts/dgenr8
mercury_toolkit-0.9.86.data/scripts/eavesdroppr
mercury_toolkit-0.9.86.data/scripts/expath
mercury_toolkit-0.9.86.data/scripts/ffiltr
mercury_toolkit-0.9.86.data/scripts/fgate
mercury_toolkit-0.9.86.data/scripts/get-awssecret
mercury_toolkit-0.9.86.data/scripts/ifthen
mercury_toolkit-0.9.86.data/scripts/ifvar
mercury_toolkit-0.9.86.data/scripts/j2df
mercury_toolkit-0.9.86.dist-info/METADATA
mercury_toolkit-0.9.86.dist-info/WHEEL
mercury_toolkit-0.9.86.dist-info/top_level.txt
mercury_toolkit-0.9.86.dist-info/RECORD
