Metadata-Version: 2.1
Name: mercury-toolkit
Version: 0.9.86
Summary: Mercury: a framework for fluid ETL and data management
Home-page: http://github.com/binarymachines/mercury
Author: Dexter Taylor
Author-email: binarymachineshop@gmail.com
License: MIT
Keywords: ETL data pipeline framework
Platform: any
Classifier: Development Status :: 4 - Beta
Classifier: License :: OSI Approved :: MIT License
Classifier: Programming Language :: Python
Classifier: Topic :: Software Development
Requires-Dist: snap-micro
Requires-Dist: docopt
Requires-Dist: arrow
Requires-Dist: Flask
Requires-Dist: itsdangerous
Requires-Dist: Jinja2
Requires-Dist: kafka
Requires-Dist: MarkupSafe
Requires-Dist: PyYAML
Requires-Dist: SQLAlchemy
Requires-Dist: SQLAlchemy-Utils
Requires-Dist: Werkzeug
Requires-Dist: requests
Requires-Dist: boto3
Requires-Dist: botocore
Requires-Dist: raven
Requires-Dist: redis
Requires-Dist: sh
Requires-Dist: pgpubsub
Requires-Dist: plumbum
